MANIFEST.in
README.md
setup.py
bin/compile_library.sh
graph_lib/README.rst
graph_lib/__init__.py
graph_lib/__init__.pyc
graph_lib/examples.ipynb
graph_lib/routines.py
graph_lib/routines.pyc
graph_lib.egg-info/PKG-INFO
graph_lib.egg-info/SOURCES.txt
graph_lib.egg-info/dependency_links.txt
graph_lib.egg-info/not-zip-safe
graph_lib.egg-info/requires.txt
graph_lib.egg-info/top_level.txt
graph_lib/.ipynb_checkpoints/examples-checkpoint.ipynb
graph_lib/graph/Unknown.smat
graph_lib/graph/Unknown_seed.smat
graph_lib/graph/Unknown_sys.smat
graph_lib/graph/celegans.smat
graph_lib/graph/minnesota.smat
graph_lib/graph/minnesota_R.smat
graph_lib/graph/minnesota_ids.smat
graph_lib/graph/minnesota_weighted.smat
graph_lib/graph/minnesota_weighted_seed.smat
graph_lib/graph/usps_3nn.smat
graph_lib/graph/usps_3nn_seed.smat
graph_lib/lib/MQI.cpp
graph_lib/lib/MQI.o
graph_lib/lib/MQI_c_interface.cpp
graph_lib/lib/aclpagerank.cpp
graph_lib/lib/aclpagerank.o
graph_lib/lib/aclpagerank_weighted.cpp
graph_lib/lib/densest_subgraph.cpp
graph_lib/lib/graph_check.cpp
graph_lib/lib/maxflow.cpp
graph_lib/lib/maxflow.o
graph_lib/lib/ppr_path.cpp
graph_lib/lib/proxl1PRaccel.cpp
graph_lib/lib/sweepcut.cpp
graph_lib/lib/sweepcut.o
graph_lib/lib/graph_lib_test/MQI_test.cpp
graph_lib/lib/graph_lib_test/MQI_test.o
graph_lib/lib/graph_lib_test/Makefile
graph_lib/lib/graph_lib_test/aclpagerank
graph_lib/lib/graph_lib_test/aclpagerank_test.cpp
graph_lib/lib/graph_lib_test/aclpagerank_test.o
graph_lib/lib/graph_lib_test/aclpagerank_weighted_test.cpp
graph_lib/lib/graph_lib_test/densest_subgraph_test.cpp
graph_lib/lib/graph_lib_test/ppr_path_test.cpp
graph_lib/lib/graph_lib_test/proxl1PRaccel_test.cpp
graph_lib/lib/graph_lib_test/readData.cpp
graph_lib/lib/graph_lib_test/readData.o
graph_lib/lib/graph_lib_test/sweepcut
graph_lib/lib/graph_lib_test/sweepcut_test.cpp
graph_lib/lib/graph_lib_test/sweepcut_test.o
graph_lib/lib/graph_lib_test/test_all.py
graph_lib/lib/graph_lib_test/correct_output/MQI/minnesota_results.smat
graph_lib/lib/graph_lib_test/correct_output/aclpagerank/Unknown_set.smat
graph_lib/lib/graph_lib_test/correct_output/aclpagerank/Unknown_values.smat
