Metadata-Version: 1.0
Name: graph-lib
Version: 0.4.8
Summary: A set of useful diffusion related graph algorithm
Home-page: https://github.com/MengLiuPurdue/graph_lib
Author: Meng Liu, David F. Gleich
Author-email: liu1740@purdue.edu
License: GPL
Platform: UNKNOWN
